LICENSE
MANIFEST.in
README.md
setup.py
commands/__init__.py
commands/base.py
commands/mixins.py
commands/services.py
commands/types.py
commands/urls.py
commands/views.py
commands/decorators/__init__.py
commands/decorators/normalizer.py
commands/decorators/plugin.py
commands/decorators/singleton.py
commands/decorators/validator.py
commands/decorators/__pycache__/__init__.cpython-34.pyc
commands/decorators/__pycache__/normalizer.cpython-34.pyc
commands/decorators/__pycache__/plugin.cpython-34.pyc
commands/decorators/__pycache__/singleton.cpython-34.pyc
commands/decorators/__pycache__/validator.cpython-34.pyc
commands/static/commands/commandAjax.js
commands/static/commands/commandDefinition.js
commands/static/commands/commandService.js
commands/static/commands/commandValidation.js
commands/templates/commands/scripts.html
django_commands.egg-info/PKG-INFO
django_commands.egg-info/SOURCES.txt
django_commands.egg-info/dependency_links.txt
django_commands.egg-info/top_level.txt