Metadata-Version: 1.1
Name: django-commands
Version: 0.6
Summary: A django app that provides a plugin type model for integrating the front and backend.
Home-page: https://github.com/RutledgePaulV/django-commands
Author: Paul Rutledge
Author-email: paul.v.rutledge@gmail.com
License: BSD
Keywords: django command strategy plugin
Platform: UNKNOWN
Classifier: Environment :: Web Environment
Classifier: Framework :: Django
Classifier: Intended Audience :: Developers
Classifier: License :: OSI Approved :: BSD License
Classifier: Operating System :: OS Independent
Classifier: Programming Language :: Python
Classifier: Programming Language :: Python :: 3
Classifier: Programming Language :: Python :: 3.2
Classifier: Programming Language :: Python :: 3.3
Classifier: Programming Language :: Python :: 3.4
Classifier: Topic :: Internet :: WWW/HTTP
Classifier: Topic :: Internet :: WWW/HTTP :: Dynamic Content
